uptodate/__init__.py
uptodate/cli.py
uptodate/core.py
uptodate/tests/__init__.py
uptodate/tests/test_PyPI.py
uptodate/tests/test_RequirementsScanner.py
uptodate/tests/test_UpToDate.py
uptodate-0.3.4.dist-info/entry_points.txt
uptodate-0.3.4.dist-info/LICENSE
uptodate-0.3.4.dist-info/WHEEL
uptodate-0.3.4.dist-info/METADATA
uptodate-0.3.4.dist-info/RECORD
