Metadata-Version: 2.1
Name: uptodate
Version: 0.3.4
Summary: Command line script checking if your requirements are uptodate
Home-page: https://gitlab.com/havk/uptodate
License: UNKNOWN
Keywords: requirements, requirements.txt, uptodate
Author: Paweł Jastrzębski
Author-email: pj@napcode.eu
Classifier: License :: OSI Approved :: MIT License
Requires-Dist: typer==0.2.1
Requires-Dist: requests==2.23.0
Requires-Dist: rich==2.0.0
